pygpm/__init__.py
pygpm/__main__.py
pygpm/clean.py
pygpm/command.py
pygpm/config.py
pygpm/core.py
pygpm/help.py
pygpm/list.py
pygpm/logging.py
pygpm/main_parser.py
pygpm/parser.py
pygpm/status.py
pygpm/track.py
pygpm/util.py
pygpm/config/default.ini
pygpm-0.1.4.dist-info/LICENSE.txt
pygpm-0.1.4.dist-info/METADATA
pygpm-0.1.4.dist-info/WHEEL
pygpm-0.1.4.dist-info/entry_points.txt
pygpm-0.1.4.dist-info/top_level.txt
pygpm-0.1.4.dist-info/RECORD
